nitro/__init__.py
nitro/cli.py
nitro/commands/__init__.py
nitro/commands/build.py
nitro/commands/check.py
nitro/commands/clean.py
nitro/commands/deploy.py
nitro/commands/dev.py
nitro/commands/export.py
nitro/commands/info.py
nitro/commands/init.py
nitro/commands/new.py
nitro/commands/preview.py
nitro/commands/routes.py
nitro/commands/serve.py
nitro/core/__init__.py
nitro/core/bundler.py
nitro/core/cache.py
nitro/core/config.py
nitro/core/env.py
nitro/core/generator.py
nitro/core/images.py
nitro/core/islands.py
nitro/core/page.py
nitro/core/renderer.py
nitro/core/server.py
nitro/core/watcher.py
nitro/plugins/__init__.py
nitro/plugins/base.py
nitro/plugins/loader.py
nitro/templates/default/README.md
nitro/templates/default/nitro.config.py
nitro/templates/default/src/components/.keep
nitro/templates/default/src/components/__init__.py
nitro/templates/default/src/components/footer.py
nitro/templates/default/src/components/header.py
nitro/templates/default/src/data/.keep
nitro/templates/default/src/data/site.json
nitro/templates/default/src/pages/.keep
nitro/templates/default/src/pages/__init__.py
nitro/templates/default/src/pages/index.py
nitro/templates/default/src/styles/main.css
nitro/utils/__init__.py
nitro/utils/logger.py
nitro_cli-1.0.8.dist-info/licenses/LICENSE
nitro_cli-1.0.8.dist-info/METADATA
nitro_cli-1.0.8.dist-info/WHEEL
nitro_cli-1.0.8.dist-info/entry_points.txt
nitro_cli-1.0.8.dist-info/top_level.txt
nitro_cli-1.0.8.dist-info/RECORD
