Metadata-Version: 2.4
Name: nitro-cli
Version: 1.0.8
Summary: Build static sites with Python code instead of template engines
Author-email: Sean Nieuwoudt <sean@nitro.sh>
Project-URL: Homepage, https://github.com/nitro-sh/nitro-cli
Project-URL: Documentation, https://nitro-cli.readthedocs.io
Project-URL: Repository, https://github.com/nitro-sh/nitro-cli
Project-URL: Issues, https://github.com/nitro-sh/nitro-cli/issues
Keywords: static-site-generator,cli,html,nitro,web,ssg
Classifier: Operating System :: OS Independent
Classifier: Development Status :: 4 - Beta
Classifier: Intended Audience :: Developers
Classifier: License :: OSI Approved :: MIT License
Classifier: Programming Language :: Python :: 3
Classifier: Programming Language :: Python :: 3.8
Classifier: Programming Language :: Python :: 3.9
Classifier: Programming Language :: Python :: 3.10
Classifier: Programming Language :: Python :: 3.11
Classifier: Programming Language :: Python :: 3.12
Classifier: Programming Language :: Python :: 3.13
Classifier: Programming Language :: Python :: 3.14
Classifier: Topic :: Software Development :: Build Tools
Classifier: Topic :: Internet :: WWW/HTTP :: Site Management
Requires-Python: >=3.8
License-File: LICENSE
Requires-Dist: click>=8.1.0
Requires-Dist: watchdog>=4.0.0
Requires-Dist: rich>=13.0.0
Requires-Dist: pyyaml>=6.0.1
Requires-Dist: aiohttp>=3.9.0
Requires-Dist: aiofiles>=23.0.0
Requires-Dist: csscompressor>=0.9.5
Requires-Dist: minify-html>=0.15.0
Requires-Dist: pillow>=10.0.0
Requires-Dist: nitro-ui>=1.0.6
Requires-Dist: nitro-datastore>=1.0.2
Requires-Dist: nitro-dispatch>=1.0.0
Requires-Dist: beautifulsoup4>=4.12.0
Provides-Extra: dev
Requires-Dist: pytest>=8.0.0; extra == "dev"
Requires-Dist: html5lib>=1.1; extra == "dev"
Requires-Dist: black>=24.0.0; extra == "dev"
Requires-Dist: flake8>=7.0.0; extra == "dev"
Provides-Extra: markdown
Requires-Dist: python-frontmatter>=1.1.0; extra == "markdown"
Requires-Dist: markdown>=3.6.0; extra == "markdown"
Provides-Extra: images
Requires-Dist: pillow-avif-plugin>=1.3.0; extra == "images"
Provides-Extra: dotenv
Requires-Dist: python-dotenv>=1.0.0; extra == "dotenv"
Dynamic: license-file
